spatialclique/__init__.py
spatialclique/spatialclique.py
spatialclique-0.1.dist-info/LICENSE
spatialclique-0.1.dist-info/METADATA
spatialclique-0.1.dist-info/WHEEL
spatialclique-0.1.dist-info/top_level.txt
spatialclique-0.1.dist-info/RECORD
