Metadata-Version: 2.1
Name: spatialclique
Version: 0.1
Summary: Maximum clique for 2D or 3D points
Home-page: https://github.com/pjhartzell/max-clique
Author: Preston Hartzell
Author-email: preston.hartzell@gmail.com
License: MIT
Keywords: maximum clique spatial
Platform: UNKNOWN
Requires-Dist: numpy
Requires-Dist: networkx
